{
  "name": "VALORAE Proxy",
  "version": "21.12.0",
  "release": "21.12.361-full-stack-alignment-audit-v329",
  "patch": "21.12.361-full-stack-alignment-audit-v329",
  "releasePatch": "21.12.361-full-stack-alignment-audit-v329",
  "latestInternalPatch": "21.12.361-full-stack-alignment-audit-v329",
  "description": "Proxy v329 audita segurança, contratos, rede, metadados e integração com o APK v509.",
  "contract": "APK v509 / Proxy 21.12.361 + mobile protocol 2026.07.10.10 + asset modal delivery v4; roteador protegido, ciclo de rede cancelável, metadados e contratos auditados.",
  "primaryMobileRoute": "/api/v1/mobile/practical-sync",
  "majorCapabilities": [
    "segurança uniforme",
    "contratos alinhados",
    "logo oficial prioritário",
    "auditoria automática"
  ],
  "cleanup": "proxy-clean-v207-2026-07-03",
  "cleanupDescription": "Pacote limpo com gateway único, monitor central e entrega progressiva dos modais de AÇÃO e FII.",
  "releaseDate": "2026-07-13",
  "checkpoint": "full-stack-alignment-audit-v329",
  "title": "Proxy v329 — Auditoria e alinhamento integral APK/Proxy",
  "summary": "Endurece o roteador, corrige parsing e confirma o contrato integral com o APK v509.",
  "publicVersion": "21.12.361",
  "label": "full-stack-alignment-audit-v329",
  "updatedAt": "2026-07-13",
  "date": "2026-07-13",
  "notes": [
    "Pareado ao APK v509.",
    "Rotas mutáveis exigem token."
  ],
  "releaseNotes": [
    "Guards globais no roteador.",
    "Regex e receitas corrigidas.",
    "Logo oficial prioritário."
  ],
  "apkPair": "apk_valorae_checkpoint99_full_stack_alignment_audit_v509_AI_STUDIO_ROOT_OK_2026_07_13.zip",
  "apkVersion": "2026.07.13.05",
  "fileSize": 0,
  "highlights": [
    "Notícias por ativo restauradas.",
    "Logos compatíveis com Coil/Android.",
    "Dividend Yield histórico operacional.",
    "Sem fallback sintético."
  ],
  "validation": [
    "Suíte completa.",
    "Testes HTTP de segurança.",
    "Cross-stack APK v509."
  ],
  "proxyPair": "valorae_proxy_checkpoint361_full_stack_alignment_audit_v329_AI_STUDIO_ROOT_OK_2026_07_13.zip",
  "validations": [
    "Suíte completa.",
    "Testes HTTP de segurança.",
    "Cross-stack APK v509."
  ],
  "changes": [
    "Roteador protegido.",
    "Headers e endpoints alinhados.",
    "Metadados sincronizados."
  ],
  "contractVersion": "APK v509 / Proxy 21.12.361 + mobile protocol 2026.07.10.10 + asset modal delivery v4; roteador protegido, ciclo de rede cancelável, metadados e contratos auditados.",
  "latestVersion": "21.12.361",
  "latest_version": "21.12.361",
  "versionName": "21.12.361",
  "packageValidation": [
    "project files at ZIP root",
    "npm test",
    "npm run build",
    "npm run audit:version",
    "cross-stack APK v509"
  ]
}
